ericnbdev/__init__.py
ericnbdev/_modidx.py
ericnbdev/core.py
ericnbdev/models/__init__.py
ericnbdev/models/random_forest.py
ericnbdev-0.0.3.dist-info/LICENSE
ericnbdev-0.0.3.dist-info/METADATA
ericnbdev-0.0.3.dist-info/WHEEL
ericnbdev-0.0.3.dist-info/entry_points.txt
ericnbdev-0.0.3.dist-info/top_level.txt
ericnbdev-0.0.3.dist-info/RECORD
